[
  {
    "namespace": "hostinger-affiliate-plugin/v1",
    "firstDetectedAt": "2025-10-21T06:31:58.694Z",
    "lastDetectedAt": "2025-10-21T06:31:58.694Z",
    "domains": [
      "cms.justy.dev"
    ]
  },
  {
    "namespace": "hostinger-amplitude/v1",
    "firstDetectedAt": "2025-10-21T06:31:58.695Z",
    "lastDetectedAt": "2025-10-21T06:31:58.695Z",
    "domains": [
      "cms.justy.dev"
    ]
  },
  {
    "namespace": "pods/v1",
    "firstDetectedAt": "2025-10-21T06:31:58.698Z",
    "lastDetectedAt": "2025-10-21T06:31:58.698Z",
    "domains": [
      "cms.justy.dev"
    ]
  },
  {
    "namespace": "sitemap/v1",
    "firstDetectedAt": "2025-10-21T06:31:58.701Z",
    "lastDetectedAt": "2025-10-21T06:31:58.701Z",
    "domains": [
      "cms.justy.dev"
    ]
  },
  {
    "namespace": "akismet/v1",
    "firstDetectedAt": "2025-10-21T06:32:29.604Z",
    "lastDetectedAt": "2025-10-21T06:32:29.604Z",
    "domains": [
      "iandunn.name"
    ]
  },
  {
    "namespace": "frm-admin/v1",
    "firstDetectedAt": "2025-10-21T06:32:29.606Z",
    "lastDetectedAt": "2025-10-21T06:32:29.606Z",
    "domains": [
      "iandunn.name"
    ]
  },
  {
    "namespace": "regolith/v1",
    "firstDetectedAt": "2025-10-21T06:32:29.607Z",
    "lastDetectedAt": "2025-10-21T06:32:29.607Z",
    "domains": [
      "iandunn.name"
    ]
  },
  {
    "namespace": "syntax-highlighting-code-block/v1",
    "firstDetectedAt": "2025-10-21T06:32:29.609Z",
    "lastDetectedAt": "2025-10-21T06:32:29.609Z",
    "domains": [
      "iandunn.name"
    ]
  },
  {
    "namespace": "two-factor/1.0",
    "firstDetectedAt": "2025-10-21T06:32:29.611Z",
    "lastDetectedAt": "2025-10-21T06:32:29.611Z",
    "domains": [
      "iandunn.name"
    ]
  }
]
